tbdump/__init__.py
tbdump-1.4.dist-info/LICENSE
tbdump-1.4.dist-info/METADATA
tbdump-1.4.dist-info/WHEEL
tbdump-1.4.dist-info/top_level.txt
tbdump-1.4.dist-info/RECORD
