Metadata-Version: 2.1
Name: tbdump
Version: 1.4
Summary: Display helpful information for debbugging in case of errors/exceptions
Home-page: https://github.com/h-ohsaki/tbdump
Author: Hiroyuki Ohsaki
Author-email: ohsaki@lsnl.jp
License: UNKNOWN
Platform: UNKNOWN
Classifier: Programming Language :: Python :: 3
Classifier: License :: OSI Approved :: GNU General Public License v3 (GPLv3)
Classifier: Operating System :: OS Independent
Requires-Dist: ansiterm
